sleepguard/__init__.py
sleepguard/guard.py
sleepguard/monitors/__init__.py
sleepguard/monitors/base.py
sleepguard/monitors/cpu.py
sleepguard/monitors/factory.py
sleepguard/monitors/gpu.py
sleepguard/monitors/net.py
sleepguard/resources/__init__.py
sleepguard/resources/default_configuration.yaml
sleepguard-0.1.7.dist-info/LICENSE
sleepguard-0.1.7.dist-info/METADATA
sleepguard-0.1.7.dist-info/WHEEL
sleepguard-0.1.7.dist-info/entry_points.txt
sleepguard-0.1.7.dist-info/top_level.txt
sleepguard-0.1.7.dist-info/RECORD
