Metadata-Version: 2.1
Name: sleepguard
Version: 0.1.7
Summary: Monitor system stats and prevent system sleep when significant activity is detected.
Author-email: Reid Swanson <reid@reidswanson.com>
License: MIT License
Project-URL: Homepage, https://bitbucket.org/reidswanson/sleepguard
Keywords: sleep,suspend,power-management,keep-awake,prevent-sleep
Classifier: Programming Language :: Python :: 3
Classifier: Programming Language :: Python :: 3.12
Classifier: License :: OSI Approved :: MIT License
Classifier: Operating System :: OS Independent
Classifier: Development Status :: 3 - Alpha
Requires-Python: >=3.12
License-File: LICENSE
Requires-Dist: platformdirs
Requires-Dist: psutil
Requires-Dist: simple-parsing[yaml]
Requires-Dist: wakepy >=0.9.1
Provides-Extra: all
Requires-Dist: sleepguard[amd,bump-my-version,documentation,nvidia,testing] ; extra == 'all'
Provides-Extra: amd
Requires-Dist: pyadl ; extra == 'amd'
Provides-Extra: bump_my_version
Requires-Dist: bump-my-version ; extra == 'bump_my_version'
Provides-Extra: documentation
Requires-Dist: six ; extra == 'documentation'
Requires-Dist: sphinx ; extra == 'documentation'
Requires-Dist: sphinx-rtd-theme ; extra == 'documentation'
Requires-Dist: livereload ; extra == 'documentation'
Provides-Extra: nvidia
Requires-Dist: gputil ; extra == 'nvidia'
Provides-Extra: testing
Requires-Dist: pytest ; extra == 'testing'
